security_headers/__init__.py
security_headers/cli.py
security_headers/csv.py
security_headers/security-headers-policy.yml
security_headers/security_headers.py
security_headers_scan-0.1.0.dist-info/WHEEL
security_headers_scan-0.1.0.dist-info/METADATA
security_headers_scan-0.1.0.dist-info/RECORD
