Metadata-Version: 2.1
Name: security-headers-scan
Version: 0.1.0
Summary: 
Author: Pat
Author-email: patrick.turner@nhs.net
Requires-Python: >=3.9,<4.0
Classifier: Programming Language :: Python :: 3
Classifier: Programming Language :: Python :: 3.10
Classifier: Programming Language :: Python :: 3.9
Requires-Dist: PyYAML (>=6.0,<7.0)
Requires-Dist: certifi (>=2021.10.8,<2022.0.0)
Requires-Dist: click (>=8.0.3,<9.0.0)
Requires-Dist: python-dotenv (>=0.19.2,<0.20.0)
Requires-Dist: requests (>=2.27.1,<3.0.0)
Requires-Dist: semantic-version (>=2.9.0,<3.0.0)
